{
  "event_key": "M-FREE-1500-25",
  "label_fr": "M 1500 lib (25m)",
  "swim_count": 3,
  "swims": [
    {
      "swim_id": "20260426-129094117-1500-FREE-25",
      "swimmer_id": "129094117",
      "swimmer_slug": "kevin-buckley",
      "swimmer_name": "Kevin Buckley",
      "firstname": "Kevin",
      "lastname": "Buckley",
      "gender": "M",
      "dob": "1982-12-12",
      "age_at_meet": 43,
      "age_group": "40-44",
      "stroke": "FREE",
      "stroke_fr": "lib",
      "distance": 1500,
      "pool": 25,
      "relay": false,
      "event_key": "M-FREE-1500-25",
      "bucket_key": "M-40-44-FREE-1500-25",
      "time_sec": 1196.59,
      "splits_sec": [
        38.22,
        78.36,
        118.61,
        159.05,
        199.38,
        239.58,
        278.93,
        318.57,
        358.58,
        398.39,
        437.84,
        477.74,
        517.54,
        557.5,
        597.31,
        637.37,
        677.22,
        717.11,
        757.21,
        797.08,
        837.11,
        877.28,
        917.59,
        957.78,
        998.18,
        1038.61,
        1078.71,
        1118.79,
        1158.9
      ],
      "status": "OK",
      "place": null,
      "points": 7,
      "entrytime_sec": 1277.8,
      "meet_id": "2026-04-24-championnat-quebecois-des-maitres",
      "meet_name": "Championnat québécois des Maitres 2026",
      "meet_date": "2026-04-26",
      "meet_city": "Montréal",
      "meet_course": "SCM",
      "meet_source": "lenex",
      "set_record": false,
      "record_key": null
    },
    {
      "swim_id": "20260426-128938642-1500-FREE-25",
      "swimmer_id": "128938642",
      "swimmer_slug": "benoit-raymond",
      "swimmer_name": "Benoit Raymond",
      "firstname": "Benoit",
      "lastname": "Raymond",
      "gender": "M",
      "dob": "1982-06-11",
      "age_at_meet": 43,
      "age_group": "40-44",
      "stroke": "FREE",
      "stroke_fr": "lib",
      "distance": 1500,
      "pool": 25,
      "relay": false,
      "event_key": "M-FREE-1500-25",
      "bucket_key": "M-40-44-FREE-1500-25",
      "time_sec": 1281.44,
      "splits_sec": [
        37.1,
        78.54,
        121.02,
        163.57,
        206.58,
        249.11,
        291.99,
        334.93,
        377.85,
        420.89,
        463.61,
        506.26,
        549.38,
        591.9,
        635.07,
        678.11,
        721.09,
        764.3,
        807.38,
        851.14,
        894.71,
        938.24,
        981.8,
        1025.56,
        1069.1,
        1112.36,
        1154.99,
        1197.42,
        1239.91
      ],
      "status": "OK",
      "place": null,
      "points": 5,
      "entrytime_sec": 1447.9,
      "meet_id": "2026-04-24-championnat-quebecois-des-maitres",
      "meet_name": "Championnat québécois des Maitres 2026",
      "meet_date": "2026-04-26",
      "meet_city": "Montréal",
      "meet_course": "SCM",
      "meet_source": "lenex",
      "set_record": false,
      "record_key": null
    },
    {
      "swim_id": "20260426-128878612-1500-FREE-25",
      "swimmer_id": "128878612",
      "swimmer_slug": "sebastien-morel",
      "swimmer_name": "Sebastien Morel",
      "firstname": "Sebastien",
      "lastname": "Morel",
      "gender": "M",
      "dob": "1975-11-24",
      "age_at_meet": 50,
      "age_group": "50-54",
      "stroke": "FREE",
      "stroke_fr": "lib",
      "distance": 1500,
      "pool": 25,
      "relay": false,
      "event_key": "M-FREE-1500-25",
      "bucket_key": "M-50-54-FREE-1500-25",
      "time_sec": 1462.53,
      "splits_sec": [
        43.72,
        92.06,
        141.32,
        190.39,
        239.93,
        289.11,
        338.54,
        387.28,
        436.15,
        485.42,
        535.06,
        584.3,
        633.84,
        683.01,
        732.49,
        781.94,
        831.3,
        880.05,
        928.88,
        977.73,
        1026.83,
        1076.21,
        1125.64,
        1175.09,
        1223.95,
        1272.78,
        1320.99,
        1369.35,
        1416.94
      ],
      "status": "OK",
      "place": null,
      "points": 9,
      "entrytime_sec": 1506.15,
      "meet_id": "2026-04-24-championnat-quebecois-des-maitres",
      "meet_name": "Championnat québécois des Maitres 2026",
      "meet_date": "2026-04-26",
      "meet_city": "Montréal",
      "meet_course": "SCM",
      "meet_source": "lenex",
      "set_record": false,
      "record_key": null
    }
  ]
}