{
  "event_key": "M-MEDLEY-400-25",
  "label_fr": "M 400 qni (25m)",
  "swim_count": 2,
  "swims": [
    {
      "swim_id": "20251213-129094117-400-MEDLEY-25",
      "swimmer_id": "129094117",
      "swimmer_slug": "kevin-buckley",
      "swimmer_name": "Kevin Buckley",
      "firstname": "Kevin",
      "lastname": "Buckley",
      "gender": "M",
      "dob": "1982-12-12",
      "age_at_meet": 43,
      "age_group": "40-44",
      "stroke": "MEDLEY",
      "stroke_fr": "qni",
      "distance": 400,
      "pool": 25,
      "relay": false,
      "event_key": "M-MEDLEY-400-25",
      "bucket_key": "M-40-44-MEDLEY-400-25",
      "time_sec": 368.2,
      "splits_sec": [
        36.85,
        84.19,
        134.07,
        182.73,
        233.54,
        284.62,
        327.38
      ],
      "status": "OK",
      "place": null,
      "points": 5,
      "entrytime_sec": 360.0,
      "meet_id": "2025-12-13-coupe-des-maitres-manche-3-ouest",
      "meet_name": "Coupe des maitres manche #3 Ouest",
      "meet_date": "2025-12-13",
      "meet_city": "Montréal-Nord",
      "meet_course": "SCM",
      "meet_source": "lenex",
      "set_record": false,
      "record_key": null
    },
    {
      "swim_id": "20260424-129103861-400-MEDLEY-25",
      "swimmer_id": "129103861",
      "swimmer_slug": "matei-petrescu",
      "swimmer_name": "Matei Petrescu",
      "firstname": "Matei",
      "lastname": "Petrescu",
      "gender": "M",
      "dob": "1988-07-09",
      "age_at_meet": 37,
      "age_group": "35-39",
      "stroke": "MEDLEY",
      "stroke_fr": "qni",
      "distance": 400,
      "pool": 25,
      "relay": false,
      "event_key": "M-MEDLEY-400-25",
      "bucket_key": "M-35-39-MEDLEY-400-25",
      "time_sec": 354.16,
      "splits_sec": [
        38.49,
        84.81,
        131.03,
        175.08,
        225.32,
        274.7,
        314.95
      ],
      "status": "OK",
      "place": null,
      "points": 7,
      "entrytime_sec": 361.69,
      "meet_id": "2026-04-24-championnat-quebecois-des-maitres",
      "meet_name": "Championnat québécois des Maitres 2026",
      "meet_date": "2026-04-24",
      "meet_city": "Montréal",
      "meet_course": "SCM",
      "meet_source": "lenex",
      "set_record": false,
      "record_key": null
    }
  ]
}